dhengine/__init__.py
dhengine/animation.py
dhengine/assets.py
dhengine/audio.py
dhengine/camera.py
dhengine/clock.py
dhengine/ecs.py
dhengine/effects.py
dhengine/events.py
dhengine/maths.py
dhengine/physics.py
dhengine/scene.py
dhengine/sprite.py
dhengine/tilemap.py
dhengine/ui.py
dhengine/window.py
dhengine-0.1.0.dist-info/licenses/LICENSE
dhengine-0.1.0.dist-info/METADATA
dhengine-0.1.0.dist-info/WHEEL
dhengine-0.1.0.dist-info/top_level.txt
dhengine-0.1.0.dist-info/RECORD
